aiotodoist/__init__.py
aiotodoist/api.py
aiotodoist/managers.py
aiotodoist/subscribe.py
tests/__init__.py
tests/stubs.py
tests/test_api.py
aiotodoist-8.1.0.2.dist-info/LICENSE
aiotodoist-8.1.0.2.dist-info/METADATA
aiotodoist-8.1.0.2.dist-info/WHEEL
aiotodoist-8.1.0.2.dist-info/top_level.txt
aiotodoist-8.1.0.2.dist-info/RECORD
