Metadata-Version: 2.1
Name: aiotodoist
Version: 8.1.0.2
Summary: UNKNOWN
Home-page: https://github.com/LFLab/aio-todoist
Author: Lanfon
Author-email: lanfon72@gmail.com
License: UNKNOWN
Platform: UNKNOWN
Classifier: Development Status :: 4 - Beta
Classifier: Intended Audience :: Developers
Classifier: License :: OSI Approved :: MIT License
Classifier: Operating System :: OS Independent
Classifier: Programming Language :: Python :: 3.7
Classifier: Programming Language :: Python :: 3.8
Classifier: Programming Language :: Python :: 3.9
Requires-Python: >=3.7
Requires-Dist: aiohttp (<4.*,>=3.*)
Requires-Dist: todoist-python (>=8.*)
